leantree/__init__.py
leantree/core/__init__.py
leantree/core/abstraction.py
leantree/core/lean.py
leantree/core/lean_file.py
leantree/core/project.py
leantree/core/proof_tree.py
leantree/data_extraction/__init__.py
leantree/data_extraction/file_loader.py
leantree/data_extraction/proof_verification.py
leantree/data_extraction/tree_builder.py
leantree/data_extraction/tree_postprocessor.py
leantree/file_span.py
leantree/metavar_graph.py
leantree/repl_adapter/__init__.py
leantree/repl_adapter/ast_parser.py
leantree/repl_adapter/data.py
leantree/repl_adapter/data_extraction.py
leantree/repl_adapter/interaction.py
leantree/repl_adapter/server_pool.py
leantree/repl_adapter/singleton_trees.py
leantree/utils.py
leantree-1.0.0.dist-info/LICENSE
leantree-1.0.0.dist-info/METADATA
leantree-1.0.0.dist-info/WHEEL
leantree-1.0.0.dist-info/RECORD
