Metadata-Version: 2.3
Name: leantree
Version: 1.0.0
Summary: REPL interaction and data extraction for Lean 4.
License: MIT
Author: Matěj Kripner
Author-email: kripner@ufal.mff.cuni.cz
Requires-Python: >=3.12
Classifier: License :: OSI Approved :: MIT License
Classifier: Programming Language :: Python :: 3
Classifier: Programming Language :: Python :: 3.12
Classifier: Programming Language :: Python :: 3.13
Requires-Dist: PrettyPrintTree (>=2.0.1)
Requires-Dist: numpy (>=1.26.4)
Requires-Dist: psutil (>=6.1.0)
Requires-Dist: tqdm (>=4.67.0)
